<?xml version="1.1" encoding="UTF-8"?>
<expression:EMFExpression xmi:version="2.0" xmlns:xmi="http://www.omg.org/XMI" xmlns:expression="http:///expression.ecore" id="tMap_1=>" expression="row1.parkingtempsreel.equals(&quot;Oui&quot;) ? true : false">
  <variables name="row1.nom" value="null" talendType="id_String" nullable="true"/>
  <variables name="row1.idparking" value="null" talendType="id_String" nullable="true"/>
  <variables name="row1.commune" value="null" talendType="id_String" nullable="true"/>
  <variables name="row1.proprietaire" value="null" talendType="id_String" nullable="true"/>
  <variables name="row1.gestionnaire" value="null" talendType="id_String" nullable="true"/>
  <variables name="row1.voieentree" value="null" talendType="id_String" nullable="true"/>
  <variables name="row1.voiesortie" value="null" talendType="id_String" nullable="true"/>
  <variables name="row1.avancement" value="null" talendType="id_String" nullable="true"/>
  <variables name="row1.annee" value="null" talendType="id_Integer" nullable="true"/>
  <variables name="row1.typeparking" value="null" talendType="id_String" nullable="true"/>
  <variables name="row1.situation" value="null" talendType="id_String" nullable="true"/>
  <variables name="row1.parkingtempsreel" value="null" talendType="id_String" nullable="true"/>
  <variables name="row1.gabarit" value="null" talendType="id_String" nullable="true"/>
  <variables name="row1.capacite" value="null" talendType="id_Integer" nullable="true"/>
  <variables name="row1.capacite2rm" value="null" talendType="id_Integer" nullable="true"/>
  <variables name="row1.capacitevelo" value="null" talendType="id_Integer" nullable="true"/>
  <variables name="row1.capaciteautopartage" value="null" talendType="id_Integer" nullable="true"/>
  <variables name="row1.capacitepmr" value="null" talendType="id_Integer" nullable="true"/>
  <variables name="row1.usage" value="null" talendType="id_String" nullable="true"/>
  <variables name="row1.reglementation" value="null" talendType="id_String" nullable="true"/>
  <variables name="row1.fermeture" value="null" talendType="id_String" nullable="true"/>
  <variables name="row1.observation" value="null" talendType="id_String" nullable="true"/>
  <variables name="row1.gid" value="null" talendType="id_String" nullable="true"/>
  <variables name="row1.latitude" value="null" talendType="id_Double" nullable="true"/>
  <variables name="row1.longitude" value="null" talendType="id_Double" nullable="true"/>
</expression:EMFExpression>
